ol_openedx_course_translations/__init__.py
ol_openedx_course_translations/admin.py
ol_openedx_course_translations/apps.py
ol_openedx_course_translations/filters.py
ol_openedx_course_translations/middleware.py
ol_openedx_course_translations/models.py
ol_openedx_course_translations/tasks.py
ol_openedx_course_translations/urls.py
ol_openedx_course_translations/views.py
ol_openedx_course_translations/glossaries/machine_learning/ar.txt
ol_openedx_course_translations/glossaries/machine_learning/de.txt
ol_openedx_course_translations/glossaries/machine_learning/el.txt
ol_openedx_course_translations/glossaries/machine_learning/es-419.txt
ol_openedx_course_translations/glossaries/machine_learning/es.txt
ol_openedx_course_translations/glossaries/machine_learning/fr.txt
ol_openedx_course_translations/glossaries/machine_learning/ja.txt
ol_openedx_course_translations/glossaries/machine_learning/pt-br.txt
ol_openedx_course_translations/glossaries/machine_learning/ru.txt
ol_openedx_course_translations/management/__init__.py
ol_openedx_course_translations/management/commands/__init__.py
ol_openedx_course_translations/management/commands/sync_and_translate_language.py
ol_openedx_course_translations/management/commands/translate_course.py
ol_openedx_course_translations/migrations/0001_add_translation_logs.py
ol_openedx_course_translations/migrations/__init__.py
ol_openedx_course_translations/providers/__init__.py
ol_openedx_course_translations/providers/base.py
ol_openedx_course_translations/providers/deepl_provider.py
ol_openedx_course_translations/providers/llm_providers.py
ol_openedx_course_translations/settings/cms.py
ol_openedx_course_translations/settings/common.py
ol_openedx_course_translations/settings/lms.py
ol_openedx_course_translations/utils/__init__.py
ol_openedx_course_translations/utils/command_utils.py
ol_openedx_course_translations/utils/constants.py
ol_openedx_course_translations/utils/course_translations.py
ol_openedx_course_translations/utils/translation_sync.py
ol_openedx_course_translations-0.3.17.dist-info/METADATA
ol_openedx_course_translations-0.3.17.dist-info/WHEEL
ol_openedx_course_translations-0.3.17.dist-info/entry_points.txt
ol_openedx_course_translations-0.3.17.dist-info/licenses/LICENSE.txt
ol_openedx_course_translations-0.3.17.dist-info/RECORD
