Metadata-Version: 2.4
Name: ol-openedx-course-translations
Version: 0.3.17
Summary: An Open edX plugin to translate courses
Author: MIT Office of Digital Learning
License-Expression: BSD-3-Clause
License-File: LICENSE.txt
Keywords: Python,edx
Requires-Python: >=3.11
Requires-Dist: deepl>=1.25.0
Requires-Dist: django>=4.0
Requires-Dist: djangorestframework>=3.14.0
Requires-Dist: edx-opaque-keys
Requires-Dist: gitpython>=3.1.40
Requires-Dist: litellm>=1.80.0
Requires-Dist: polib>=1.2.0
Requires-Dist: requests>=2.31.0
Requires-Dist: srt>=3.5.3
